LICENSE
MANIFEST.in
README.md
setup.py
django_steam/__init__.py
django_steam/apps.py
django_steam/models.py
django_steam.egg-info/PKG-INFO
django_steam.egg-info/SOURCES.txt
django_steam.egg-info/dependency_links.txt
django_steam.egg-info/requires.txt
django_steam.egg-info/top_level.txt
django_steam/migrations/0001_initial.py
django_steam/migrations/__init__.py